lca_infographics/__init__.py
lca_infographics/__main__.py
lca_infographics/app.py
lca_infographics/sample_data.json
lca_infographics-0.1.0.dist-info/licenses/LICENSE
lca_infographics-0.1.0.dist-info/METADATA
lca_infographics-0.1.0.dist-info/WHEEL
lca_infographics-0.1.0.dist-info/entry_points.txt
lca_infographics-0.1.0.dist-info/top_level.txt
lca_infographics-0.1.0.dist-info/RECORD
