Metadata-Version: 2.4
Name: lca-infographics
Version: 0.1.0
Summary: LCA infographics viewer with PyQt5 and Matplotlib
Author-email: Iurii Vakaliuk <iurii.vakaliuk@tu-dresden.de>
License-Expression: MIT
Classifier: Programming Language :: Python :: 3
Classifier: Programming Language :: Python :: 3 :: Only
Classifier: Operating System :: OS Independent
Classifier: Environment :: X11 Applications :: Qt
Classifier: Topic :: Scientific/Engineering
Requires-Python: >=3.9
License-File: LICENSE
Requires-Dist: PyQt5>=5.15.9
Requires-Dist: matplotlib>=3.8
Requires-Dist: openpyxl>=3.1
Requires-Dist: numpy>=1.26
Dynamic: license-file
